datayoga_core/__init__.py
datayoga_core/block.py
datayoga_core/blocks/__init__.py
datayoga_core/blocks/add_field/__init__.py
datayoga_core/blocks/add_field/block.py
datayoga_core/blocks/add_field/block.schema.json
datayoga_core/blocks/add_field/tests/test_add_field.py
datayoga_core/blocks/azure/read_event_hub/__init__.py
datayoga_core/blocks/azure/read_event_hub/block.py
datayoga_core/blocks/azure/read_event_hub/block.schema.json
datayoga_core/blocks/cassandra/__init__.py
datayoga_core/blocks/cassandra/write/__init__.py
datayoga_core/blocks/cassandra/write/block.py
datayoga_core/blocks/cassandra/write/block.schema.json
datayoga_core/blocks/files/read_csv/__init__.py
datayoga_core/blocks/files/read_csv/block.py
datayoga_core/blocks/files/read_csv/block.schema.json
datayoga_core/blocks/filter/__init__.py
datayoga_core/blocks/filter/block.py
datayoga_core/blocks/filter/block.schema.json
datayoga_core/blocks/filter/tests/test_filter.py
datayoga_core/blocks/http/receiver/__init__.py
datayoga_core/blocks/http/receiver/block.py
datayoga_core/blocks/http/receiver/block.schema.json
datayoga_core/blocks/http/write/block.py
datayoga_core/blocks/http/write/block.schema.json
datayoga_core/blocks/http/write/tests/test_http_write.py
datayoga_core/blocks/jinja_template/__init__.py
datayoga_core/blocks/jinja_template/block.py
datayoga_core/blocks/jinja_template/block.schema.json
datayoga_core/blocks/jinja_template/tests/test_jinja_template.py
datayoga_core/blocks/map/__init__.py
datayoga_core/blocks/map/block.py
datayoga_core/blocks/map/block.schema.json
datayoga_core/blocks/map/tests/test_map.py
datayoga_core/blocks/parquet/__init__.py
datayoga_core/blocks/parquet/read/__init__.py
datayoga_core/blocks/parquet/read/block.py
datayoga_core/blocks/parquet/read/block.schema.json
datayoga_core/blocks/parquet/write/__init__.py
datayoga_core/blocks/parquet/write/block.py
datayoga_core/blocks/parquet/write/block.schema.json
datayoga_core/blocks/redis/__init__.py
datayoga_core-1.134.0.dist-info/METADATA
datayoga_core-1.134.0.dist-info/WHEEL
datayoga_core-1.134.0.dist-info/entry_points.txt
datayoga_core-1.134.0.dist-info/RECORD
