Metadata-Version: 2.1
Name: datayoga-core
Version: 1.134.0
Summary: DataYoga for Python
License: Apache-2.0
Author: DataYoga
Author-email: admin@datayoga.io
Requires-Python: >=3.8,<4.0
Classifier: Development Status :: 4 - Beta
Classifier: Intended Audience :: Developers
Classifier: License :: OSI Approved :: Apache Software License
Classifier: Programming Language :: Python :: 3
Classifier: Programming Language :: Python :: 3.8
Classifier: Programming Language :: Python :: 3.9
Classifier: Programming Language :: Python :: 3.10
Classifier: Programming Language :: Python :: 3.11
Classifier: Programming Language :: Python :: 3.12
Classifier: Programming Language :: Python :: 3.13
Classifier: Topic :: Database
Provides-Extra: azure
Provides-Extra: cassandra
Provides-Extra: db2
Provides-Extra: http
Provides-Extra: mysql
Provides-Extra: oracle
Provides-Extra: parquet
Provides-Extra: pg
Provides-Extra: redis
Provides-Extra: sqlserver
Provides-Extra: test
Requires-Dist: Jinja2 (>=3.1.2,<4.0.0)
Requires-Dist: PyMySQL (>=1.1.1,<2.0.0) ; extra == "mysql" or extra == "test"
Requires-Dist: PyYAML (>=6.0,<7.0)
Requires-Dist: SQLAlchemy (>=2.0.4,<3.0.0) ; extra == "mysql" or extra == "oracle" or extra == "pg" or extra == "sqlserver" or extra == "test"
Requires-Dist: aiohttp (>=3.8.4,<4.0.0) ; extra == "http" or extra == "test"
Requires-Dist: azure-eventhub (>=5.11.2,<6.0.0) ; extra == "azure"
Requires-Dist: azure-eventhub-checkpointstoreblob-aio (>=1.1.4,<2.0.0) ; extra == "azure"
Requires-Dist: cassandra-driver (>=3.25.0,<4.0.0) ; extra == "cassandra" or extra == "test"
Requires-Dist: certifi (>=2023.7.22,<2024.0.0)
Requires-Dist: cryptography (>=39.0.1)
Requires-Dist: fastparquet (>=2023.2.0,<2024.0.0) ; (python_version >= "3.8") and (extra == "parquet" or extra == "test")
Requires-Dist: hiredis (>=2.2.2,<3.0.0) ; extra == "redis"
Requires-Dist: ibm_db_sa (>=0.4.0,<0.5.0) ; extra == "db2" or extra == "test"
Requires-Dist: jmespath (>=1.0.0,<2.0.0)
Requires-Dist: jsonschema (>=4.4.0,<5.0.0)
Requires-Dist: mock (>=4.0.3,<5.0.0) ; extra == "test"
Requires-Dist: oracledb (>=1.2.2,<2.0.0) ; extra == "oracle" or extra == "test"
Requires-Dist: orjson (>=3.9.15,<4.0.0)
Requires-Dist: prometheus-client (>=0.16.0,<0.17.0)
Requires-Dist: psycopg2-binary (>=2.9.5,<3.0.0) ; extra == "pg" or extra == "test"
Requires-Dist: pymssql (>=2.2.7,<2.3.0) ; extra == "sqlserver" or extra == "test"
Requires-Dist: pysqlite3-binary (>=0.5.0,<0.6.0) ; sys_platform == "linux"
Requires-Dist: pytest (>=7.1.2,<8.0.0) ; extra == "test"
Requires-Dist: pytest-aioresponses (>=0.2.0,<0.3.0) ; extra == "test"
Requires-Dist: pytest-asyncio (>=0.20.2,<0.21.0) ; extra == "test"
Requires-Dist: pytest-describe (>=2.0.1,<3.0.0) ; extra == "test"
Requires-Dist: pytest-mock (>=3.7.0,<4.0.0) ; extra == "test"
Requires-Dist: pytest-timeout (>=2.1.0,<3.0.0) ; extra == "test"
Requires-Dist: redis (>=5.0.8,<6.0.0) ; extra == "redis" or extra == "test"
Requires-Dist: requests-mock (>=1.9.3,<2.0.0) ; extra == "test"
Requires-Dist: sqlglot (>=10.4.3,<11.0.0)
Requires-Dist: testcontainers (>=3.7.0,<4.0.0) ; extra == "test"
Project-URL: url, https://datayoga.io
